indiafactorlibrary/__init__.py
indiafactorlibrary/indiafactorlibrary.py
indiafactorlibrary-0.0.9.dist-info/licenses/LICENSE
indiafactorlibrary-0.0.9.dist-info/METADATA
indiafactorlibrary-0.0.9.dist-info/WHEEL
indiafactorlibrary-0.0.9.dist-info/top_level.txt
indiafactorlibrary-0.0.9.dist-info/RECORD
